find_dict_path/__init__.py
find_dict_path/find_dict_path.py
find_dict_path-0.0.1.dist-info/LICENSE
find_dict_path-0.0.1.dist-info/METADATA
find_dict_path-0.0.1.dist-info/WHEEL
find_dict_path-0.0.1.dist-info/top_level.txt
find_dict_path-0.0.1.dist-info/RECORD
