Metadata-Version: 2.1
Name: find-dict-path
Version: 0.0.1
Summary: An Pythonic Dictionary path generator 
Home-page: https://github.com/pyleo-1998/find-dict-path
Author: Ritik Gupta
Author-email: ritik.g1998@gmail.com
License: MIT
Platform: UNKNOWN
Classifier: License :: OSI Approved :: MIT License
Classifier: Programming Language :: Python :: 3.10
Classifier: Operating System :: OS Independent
Requires-Python: >=3.5
License-File: LICENSE
Provides-Extra: dev
Requires-Dist: pytest (>=7.0) ; extra == 'dev'
Requires-Dist: twine (>=4.0.2) ; extra == 'dev'
